calculaHashDadosAbertos
