Metadata-Version: 2.1
Name: calculaHashDadosAbertos
Version: 0.0.4
Summary: Retorna dados de hash dos ultimos n dias da biblioteca de dados abertos do governo
Home-page: https://github.com/masuta16/calculaHash
Author: Israel Andrade
Author-email: israndade16@hotmail.com
License: MIT License
Keywords: Pacote
Platform: UNKNOWN
